MANIFEST.in
setup.cfg
setup.py
versioneer.py
docker_storm.egg-info/PKG-INFO
docker_storm.egg-info/SOURCES.txt
docker_storm.egg-info/dependency_links.txt
docker_storm.egg-info/entry_points.txt
docker_storm.egg-info/requires.txt
docker_storm.egg-info/top_level.txt
storm/__init__.py
storm/_version.py
storm/colors.py
storm/storm.py
storm/tasks.py