Metadata-Version: 1.1
Name: docker-storm
Version: 0.1.0
Summary: Multi-cloud load-balanced orchestration for Docker
Home-page: https://github.com/ConsenSys/storm/
Author: caktux
Author-email: caktux@gmail.com
License: UNKNOWN
Platform: UNKNOWN
Classifier: Development Status :: 2 - Pre-Alpha
Classifier: Environment :: Console
Classifier: License :: OSI Approved :: MIT License
Classifier: Operating System :: MacOS :: MacOS X
Classifier: Operating System :: POSIX :: Linux
Classifier: Programming Language :: Python :: 2.7
